<?xml version="1.0" encoding="utf-8"?>
<Document>
  <Engineering version="V20" />
  <SW.Blocks.InstanceDB ID="0">
    <AttributeList>
      <AutoNumber>false</AutoNumber>
      <InstanceOfName>FB_AnalogOutputs</InstanceOfName>
      <InstanceOfType>FB</InstanceOfType>
      <Interface><Sections xmlns="http://www.siemens.com/automation/Openness/SW/Interface/v5">
  <Section Name="Input" />
  <Section Name="Output" />
  <Section Name="InOut" />
  <Section Name="Static">
    <Member Name="sNozzleOverpressureSetPoint" Datatype="&quot;FB_AnalogOutput&quot;">
      <AttributeList>
        <BooleanAttribute Name="SetPoint" SystemDefined="true">true</BooleanAttribute>
      </AttributeList>
    </Member>
    <Member Name="sFreeQW482" Datatype="&quot;FB_AnalogOutput&quot;">
      <AttributeList>
        <BooleanAttribute Name="SetPoint" SystemDefined="true">true</BooleanAttribute>
      </AttributeList>
    </Member>
    <Member Name="sVentilatorSetPoint" Datatype="&quot;FB_AnalogOutput&quot;">
      <AttributeList>
        <BooleanAttribute Name="SetPoint" SystemDefined="true">true</BooleanAttribute>
      </AttributeList>
    </Member>
    <Member Name="sPropValveClimSetPoint" Datatype="&quot;FB_AnalogOutput&quot;">
      <AttributeList>
        <BooleanAttribute Name="SetPoint" SystemDefined="true">true</BooleanAttribute>
      </AttributeList>
    </Member>
  </Section>
</Sections></Interface>
      <Name>DB_AnalogOutputs</Name>
      <Namespace />
      <Number>2113</Number>
      <ProgrammingLanguage>DB</ProgrammingLanguage>
    </AttributeList>
    <ObjectList>
      <MultilingualText ID="1" CompositionName="Comment">
        <ObjectList>
          <MultilingualTextItem ID="2" CompositionName="Items">
            <AttributeList>
              <Culture>en-US</Culture>
              <Text />
            </AttributeList>
          </MultilingualTextItem>
          <MultilingualTextItem ID="3" CompositionName="Items">
            <AttributeList>
              <Culture>fr-FR</Culture>
              <Text />
            </AttributeList>
          </MultilingualTextItem>
        </ObjectList>
      </MultilingualText>
      <MultilingualText ID="4" CompositionName="Title">
        <ObjectList>
          <MultilingualTextItem ID="5" CompositionName="Items">
            <AttributeList>
              <Culture>en-US</Culture>
              <Text />
            </AttributeList>
          </MultilingualTextItem>
          <MultilingualTextItem ID="6" CompositionName="Items">
            <AttributeList>
              <Culture>fr-FR</Culture>
              <Text />
            </AttributeList>
          </MultilingualTextItem>
        </ObjectList>
      </MultilingualText>
    </ObjectList>
  </SW.Blocks.InstanceDB>
</Document>